{   
    "contactos" : [
                    {
                        "nombre": "IVAN",
                        "apellidos": "CASTRO",
                        "edad"  : 43,
                        "estadocivil": "Casado",
                        "contacto": [ 
                            {"personal":32256757},
                            {"correo":"icastror@hotmail.com"},
                            {"laboral":32256757}
                        ]
                    },
                    {
                        "nombre": "MOISES",
                        "apellidos": "MAZO",
                        "edad"  : 17,
                        "estadocivil": "Soltero",
                        "contacto": [ 
                            {"personal":6576576},
                            {"correo":"mmazo@hotmail.com"},
                            {"laboral":634267574}
                        ]
                    }
                ]
}